xsect/__init__.py
xsect/calc/__init__.py
xsect/calc/angle.py
xsect/calc/angle_test.py
xsect/calc/boundary.py
xsect/calc/boundary_test.py
xsect/calc/cross_section.py
xsect/calc/cross_section_test.py
xsect/calc/cruciform.py
xsect/calc/cruciform_test.py
xsect/calc/double_angle.py
xsect/calc/double_angle_test.py
xsect/calc/i_beam.py
xsect/calc/i_beam_test.py
xsect/calc/multi.py
xsect/calc/multi_test.py
xsect/calc/polygon.py
xsect/calc/polygon_test.py
xsect/calc/round.py
xsect/calc/round_test.py
xsect/calc/t_beam.py
xsect/calc/t_beam_test.py
xsect/config/__init__.py
xsect/config/_matplotlib.py
xsect/data/__init__.py
xsect/data/_make_db.py
xsect/data/config_db.py
xsect/data/query_db.py
xsect/data/query_db_test.py
xsect/data/xsect.sqlite
xsect-1.1.2.dist-info/LICENSE
xsect-1.1.2.dist-info/METADATA
xsect-1.1.2.dist-info/WHEEL
xsect-1.1.2.dist-info/top_level.txt
xsect-1.1.2.dist-info/RECORD
