Metadata-Version: 2.1
Name: xsect
Version: 1.1.2
Summary: Contains tools for calculating structural member cross sectional properties and databases of standard cross sectional properties.
Home-page: https://github.com/mpewsey/xsect
Author: Matt Pewsey
License: BSD 3-Clause License
Keywords: civil-engineering
Platform: UNKNOWN
Classifier: Programming Language :: Python :: 2.7
Classifier: Programming Language :: Python :: 3.5
Classifier: Programming Language :: Python :: 3.6
Classifier: Programming Language :: Python :: 3.7
Classifier: Operating System :: OS Independent
Classifier: License :: OSI Approved :: BSD License
Requires-Python: >=2.7,!=3.0,!=3.1,!=3.2,!=3.3,!=3.4
Requires-Dist: numpy (>=1.14.5)
Requires-Dist: pandas (>=0.23.0)
Requires-Dist: matplotlib (>=2.2.2)
Provides-Extra: docs
Requires-Dist: docutils (==0.14) ; extra == 'docs'
Requires-Dist: numpydoc (>=0.8.0) ; extra == 'docs'
Provides-Extra: test
Requires-Dist: pytest (>=3.5.1) ; extra == 'test'
Requires-Dist: pytest-cov (>=2.5.1) ; extra == 'test'
Requires-Dist: codecov (>=2.0.15) ; extra == 'test'
